pgq/__init__.py
pgq/apps.py
pgq/commands.py
pgq/decorators.py
pgq/exceptions.py
pgq/models.py
pgq/py.typed
pgq/queue.py
pgq/migrations/0001_initial.py
pgq/migrations/__init__.py
django_pg_queue-0.8.2.dist-info/LICENSE
django_pg_queue-0.8.2.dist-info/METADATA
django_pg_queue-0.8.2.dist-info/WHEEL
django_pg_queue-0.8.2.dist-info/top_level.txt
django_pg_queue-0.8.2.dist-info/RECORD
