Metadata-Version: 2.1
Name: django-pg-queue
Version: 0.8.2
Summary: UNKNOWN
Home-page: https://github.com/SweetProcess/django-pg-queue
Author: SweetProcess
Author-email: support@sweetprocess.com
License: BSD
Platform: UNKNOWN
License-File: LICENSE
Requires-Dist: Django >=2.1
